litron/main.py
tskr/__init__.py
tskr/test.py
tskr/parts/AES_crypt.py
litron-0.0.0.dist-info/METADATA
litron-0.0.0.dist-info/WHEEL
litron-0.0.0.dist-info/top_level.txt
litron-0.0.0.dist-info/RECORD
