Metadata-Version: 2.1
Name: litron
Version: 0.0.0
Summary: nlp tool
Home-page: https://github.co.jp/
Author: team_LITRON
Author-email: dummy@dummy.com
License: CC0 v1.0
Platform: UNKNOWN
Classifier: Programming Language :: Python :: 3
Classifier: Topic :: Software Development :: Libraries
Classifier: License :: CC0 1.0 Universal (CC0 1.0) Public Domain Dedication
